calc.py
rio_simple_calc-0.0.1.dist-info/LICENSE
rio_simple_calc-0.0.1.dist-info/METADATA
rio_simple_calc-0.0.1.dist-info/WHEEL
rio_simple_calc-0.0.1.dist-info/top_level.txt
rio_simple_calc-0.0.1.dist-info/RECORD
